crjbsim/__init__.py
crjbsim/asncio_des.py
crjbsim/des_aware_logging.py
crjbsim/discrete_event_scheduler.py
crjbsim/scenario_test.py
crjbsim/sim.py
crjbsim/time_provider.py
crjbsim-1.3.dist-info/METADATA
crjbsim-1.3.dist-info/WHEEL
crjbsim-1.3.dist-info/top_level.txt
crjbsim-1.3.dist-info/RECORD
